tpds_extension/ta010_support/extension.yaml
tpds_extension/ta010_support/setup.py
tpds_extension/ta010_support/version.py
tpds_extension/ta010_support/backend/__init__.py
tpds_extension/ta010_support/backend/ta010.yaml
tpds_extension/ta010_support/backend/api/__init__.py
tpds_extension/ta010_support/backend/api/apis.py
tpds_extension/ta010_support/backend/api/model.py
tpds_extension/ta010_support/backend/api/base/ECC204_TA010_base.xml
tpds_extension/ta010_support/backend/usecases/__init__.py
tpds_extension/ta010_support/backend/usecases/asymm_auth_ta010/__init__.py
tpds_extension/ta010_support/backend/usecases/asymm_auth_ta010/api.py
tpds_extension/ta010_support/backend/usecases/asymm_auth_ta010/asymm_auth.py
tpds_extension/ta010_support/backend/usecases/proto_provision/__init__.py
tpds_extension/ta010_support/backend/usecases/proto_provision/asymm_auth/__init__.py
tpds_extension/ta010_support/backend/usecases/proto_provision/asymm_auth/asymm_auth.py
tpds_extension/ta010_support/backend/usecases/proto_provision/certs/__init__.py
tpds_extension/ta010_support/backend/usecases/proto_provision/certs/certs.py
tpds_extension/ta010_support/backend/usecases/proto_provision/certs/create_cert_defs.py
tpds_extension/ta010_support/backend/usecases/proto_provision/certs/x509_find_elements.py
tpds_extension/ta010_support/backend/usecases/proto_provision/connect/__init__.py
tpds_extension/ta010_support/backend/usecases/proto_provision/connect/connect.py
tpds_extension/ta010_support/backend/usecases/proto_provision/helper/__init__.py
tpds_extension/ta010_support/backend/usecases/proto_provision/helper/defines.py
tpds_extension/ta010_support/backend/usecases/proto_provision/helper/helper.py
tpds_extension/ta010_support/backend/usecases/proto_provision/helper/keys.py
tpds_extension/ta010_support/backend/usecases/proto_provision/helper/utils.py
tpds_extension/ta010_support/backend/usecases/proto_provision/symm_auth/__init__.py
tpds_extension_ta010_support-1.6.3.dist-info/METADATA
tpds_extension_ta010_support-1.6.3.dist-info/WHEEL
tpds_extension_ta010_support-1.6.3.dist-info/top_level.txt
tpds_extension_ta010_support-1.6.3.dist-info/RECORD
